{
  "generated_at": "Fri Feb 13 19:55:26 2026",
  "channels": [
    {
      "channel_number": 1,
      "name": "t sports",
      "logo": "http://tvassets.roarzone.info/images/102.png",
      "group": "sports",
      "url": "https://edge2.roarzone.info:8444/roarzone/edge2/tsports/index.m3u8?token=a2b0d7a0b4e2563edc90f9f40da7ae62448d6013-3a7c0e68bea13eab9cbcf0f9db4890b4-1771016020-1771012420",
      "stream_path": "edge2/tsports"
    },
    {
      "channel_number": 8,
      "name": "sony ten 1",
      "logo": "http://tvassets.roarzone.info/images/20.png",
      "group": "sports",
      "url": "https://edge2.roarzone.info:8444/roarzone/edge2/sony-sports-1-hd/index.m3u8?token=04d2521775535de5a31122db5d204a3bc8ed6a3a-cf84c301dc713136b8fda4e6f8ad0a0a-1771016021-1771012421",
      "stream_path": "edge2/sony-sports-1-hd"
    },
    {
      "channel_number": 9,
      "name": "sony ten 2",
      "logo": "http://tvassets.roarzone.info/images/21.png",
      "group": "sports",
      "url": "https://edge2.roarzone.info:8444/roarzone/edge2/sony-sports-2-hd/index.m3u8?token=59010757f92b766725c61489e79b27b22e15ce96-5217977d87526130bd2496670f46e469-1771016021-1771012421",
      "stream_path": "edge2/sony-sports-2-hd"
    },
    {
      "channel_number": 10,
      "name": "sony ten 3",
      "logo": "http://tvassets.roarzone.info/images/22.png",
      "group": "sports",
      "url": "https://edge2.roarzone.info:8444/roarzone/edge2/sony-sports-3-hd/index.m3u8?token=1f2a7da6d8f73e0dca508c1c0656a28439da4d2c-79b98a3ff03f0f5b0c1a6e538f973069-1771016021-1771012421",
      "stream_path": "edge2/sony-sports-3-hd"
    },
    {
      "channel_number": 11,
      "name": "sony six",
      "logo": "http://tvassets.roarzone.info/images/24.png",
      "group": "sports",
      "url": "https://edge2.roarzone.info:8444/roarzone/edge2/sony-sports-5-hd/index.m3u8?token=1858817648173c8928f49c7b991c6a50a680a3c0-7edd43952b498a113d55f3eb5eb8880e-1771016021-1771012421",
      "stream_path": "edge2/sony-sports-5-hd"
    },
    {
      "channel_number": 15,
      "name": "dubai sports",
      "logo": "http://tvassets.roarzone.info/images/dubai-sports.png",
      "group": "sports",
      "url": "https://edge2.roarzone.info:8444/roarzone/bk/dubai-sports/index.m3u8?token=005e984061fc2711205dd281953e49c07e2fb47f-b477cc1bc5885b2f797e49f2693b3e1b-1771016021-1771012421",
      "stream_path": "bk/dubai-sports"
    },
    {
      "channel_number": 17,
      "name": "star gold select",
      "logo": "http://tvassets.roarzone.info/images/75.png",
      "group": "hindi",
      "url": "https://edge2.roarzone.info:8444/roarzone/bk/72/index.m3u8?token=868b61e3b17550888840fecf68a66f390f341e24-97833473d0adb1fe2c9ab48ad40b0570-1771016021-1771012421",
      "stream_path": "bk/72"
    },
    {
      "channel_number": 21,
      "name": "colors",
      "logo": "http://tvassets.roarzone.info/images/68.png",
      "group": "hindi",
      "url": "https://edge2.roarzone.info:8444/roarzone/bk/68/index.m3u8?token=d5595908f9097f32e39695e9506ba2dc4370884b-2282c0deccfbd5af4ba1437e2df0c185-1771016021-1771012421",
      "stream_path": "bk/68"
    },
    {
      "channel_number": 27,
      "name": "star plus",
      "logo": "http://tvassets.roarzone.info/images/67.png",
      "group": "hindi",
      "url": "https://edge2.roarzone.info:8444/roarzone/bk/67/index.m3u8?token=04e79c0387721483baa12d0f1a982aac9e40fe27-8ca99bb7035b0eb47d3d7c1d644d119c-1771016021-1771012421",
      "stream_path": "bk/67"
    },
    {
      "channel_number": 41,
      "name": "natgeo",
      "logo": "http://tvassets.roarzone.info/images/35.png",
      "group": "documentary",
      "url": "https://edge2.roarzone.info:8444/roarzone/bk/35/index.m3u8?token=fc4b1428a60ab94f7c7f4a4dcc0ce226a21ac298-e5512c145558ee81ab5271282141bcab-1771016021-1771012421",
      "stream_path": "bk/35"
    },
    {
      "channel_number": 43,
      "name": "star jalsha",
      "logo": "http://tvassets.roarzone.info/images/30.png",
      "group": "inbangla",
      "url": "https://edge2.roarzone.info:8444/roarzone/bk/30/index.m3u8?token=0fa5652195b532bacaa5a0d0f294aee1591d7219-6229c046adcf2d44589eb7d0b69d421b-1771016021-1771012421",
      "stream_path": "bk/30"
    },
    {
      "channel_number": 44,
      "name": "star jalsha movies",
      "logo": "http://tvassets.roarzone.info/images/31.png",
      "group": "inbangla",
      "url": "https://edge2.roarzone.info:8444/roarzone/bk/31/index.m3u8?token=91a1da2979ca9885d1ff3b15bde3dda26846ffd3-f2d8601d1f4ff9d34e21525f527610aa-1771016021-1771012421",
      "stream_path": "bk/31"
    },
    {
      "channel_number": 47,
      "name": "colors bangla",
      "logo": "http://tvassets.roarzone.info/images/66.png",
      "group": "inbangla",
      "url": "https://edge2.roarzone.info:8444/roarzone/bk/66/index.m3u8?token=af9a9553e9434b98195d5ffcc1998d974d389a78-b8a7f898f87f79af2da13776b6d4c435-1771016021-1771012421",
      "stream_path": "bk/66"
    },
    {
      "channel_number": 50,
      "name": "nick",
      "logo": "http://tvassets.roarzone.info/images/55.png",
      "group": "kids",
      "url": "https://edge2.roarzone.info:8444/roarzone/bk/55/index.m3u8?token=621eae8e19334cbc12af1a6e4f5eaf00a237709b-400dd42c0ba4b7cb024573f351f37152-1771016021-1771012421",
      "stream_path": "bk/55"
    },
    {
      "channel_number": 54,
      "name": "star movies",
      "logo": "http://tvassets.roarzone.info/images/starmovies.png",
      "group": "english",
      "url": "https://edge2.roarzone.info:8444/roarzone/bk/starmovies/index.m3u8?token=dd561abd1a3cfbd63cae6965f06c14ba85e779ae-fef928bd4b9853041a1acd7a2154464e-1771016021-1771012421",
      "stream_path": "bk/starmovies"
    },
    {
      "channel_number": 57,
      "name": "dw news",
      "logo": "http://tvassets.roarzone.info/images/85.png",
      "group": "english",
      "url": "https://edge2.roarzone.info:8444/roarzone/bk/85/index.m3u8?token=f598074347ab422701007630a63d82aa96745673-8e56d265a49674dc782dbd96566d876a-1771016021-1771012421",
      "stream_path": "bk/85"
    },
    {
      "channel_number": 58,
      "name": "al jazeera",
      "logo": "http://tvassets.roarzone.info/images/89.png",
      "group": "english",
      "url": "https://edge2.roarzone.info:8444/roarzone/bk/89/index.m3u8?token=f0d2b2a8499df81541b54d8f3f1c0be282ac1a38-969e990c552c773ea6dd57a2f42e22c8-1771016021-1771012421",
      "stream_path": "bk/89"
    },
    {
      "channel_number": 59,
      "name": "gaan bangla",
      "logo": "http://tvassets.roarzone.info/images/58.png",
      "group": "music",
      "url": "https://edge2.roarzone.info:8444/roarzone/bk/58/index.m3u8?token=8eb0fa7c843ce8288527c23963d96bf25d854a04-0adaaf7fbfc8ba5ce02c440e613f532e-1771016021-1771012421",
      "stream_path": "bk/58"
    },
    {
      "channel_number": 60,
      "name": "9xm",
      "logo": "http://tvassets.roarzone.info/images/48.png",
      "group": "music",
      "url": "https://edge2.roarzone.info:8444/roarzone/bk/48/index.m3u8?token=f3492606e244bf45b8bef925cd29412a443a3a71-cff02b7d1f9e32d0fe8afbbe8fa0ce01-1771016021-1771012421",
      "stream_path": "bk/48"
    },
    {
      "channel_number": 64,
      "name": "nagorik tv",
      "logo": "http://tvassets.roarzone.info/images/59.png",
      "group": "bangla",
      "url": "https://edge2.roarzone.info:8444/roarzone/edge2/nagorik/index.m3u8?token=77c1ed274726e82f11338a5963b1401e594ebeae-39f3fc5ffc87dc2138971e5c80a8a06b-1771016021-1771012421",
      "stream_path": "edge2/nagorik"
    },
    {
      "channel_number": 65,
      "name": "channel 24",
      "logo": "http://tvassets.roarzone.info/images/5.png",
      "group": "bangla",
      "url": "https://edge2.roarzone.info:8444/roarzone/edge2/channel24/index.m3u8?token=a4a0594c2d3616efbfe536a777f7163b52701f0e-54771c99878ae40c4cfe255a6ce4a973-1771016021-1771012421",
      "stream_path": "edge2/channel24"
    },
    {
      "channel_number": 67,
      "name": "ekushy tv",
      "logo": "http://tvassets.roarzone.info/images/65.png",
      "group": "bangla",
      "url": "https://edge2.roarzone.info:8444/roarzone/bk/65/index.m3u8?token=584e61259dd6c90e3f14cfee6ab3367a57fcc631-28dfc5de142edceb01e05699826b4bb2-1771016021-1771012421",
      "stream_path": "bk/65"
    },
    {
      "channel_number": 69,
      "name": "atn bangla",
      "logo": "http://tvassets.roarzone.info/images/2.png",
      "group": "bangla",
      "url": "https://edge2.roarzone.info:8444/roarzone/bk/2/index.m3u8?token=6a975b2a16cb679325976f6d7ae6c29c9574303f-12ff12aa9e474793054bf485b6f71c49-1771016021-1771012421",
      "stream_path": "bk/2"
    },
    {
      "channel_number": 73,
      "name": "boishakhi tv",
      "logo": "http://tvassets.roarzone.info/images/61.png",
      "group": "bangla",
      "url": "https://edge2.roarzone.info:8444/roarzone/bk/61/index.m3u8?token=8b4317e12eed3e38718be386fd671d39ae51b58d-c937afa90ab5ee5bc2ad77ece284b9eb-1771016021-1771012421",
      "stream_path": "bk/61"
    },
    {
      "channel_number": 74,
      "name": "btv",
      "logo": "http://tvassets.roarzone.info/images/53.png",
      "group": "bangla",
      "url": "https://edge2.roarzone.info:8444/roarzone/bk/53/index.m3u8?token=be9b14ba115c6449e9c638354b40b8be64a6358f-28a526e505d4781879aed51d9defd7c4-1771016021-1771012421",
      "stream_path": "bk/53"
    },
    {
      "channel_number": 75,
      "name": "btv world",
      "logo": "http://tvassets.roarzone.info/images/84.png",
      "group": "bangla",
      "url": "https://edge2.roarzone.info:8444/roarzone/bk/84/index.m3u8?token=82f58c5ce667e2e83e817ae599dce5ccc9a27934-f91d6062332fa274f49a818c2d9fb195-1771016021-1771012421",
      "stream_path": "bk/84"
    },
    {
      "channel_number": 76,
      "name": "channel 9",
      "logo": "http://tvassets.roarzone.info/images/4.png",
      "group": "bangla",
      "url": "https://edge2.roarzone.info:8444/roarzone/bk/4/index.m3u8?token=7ded8d7b061b8de0504b57bd6b0dc94f4dcccfd0-522583043b7884aed325d113e9d33194-1771016021-1771012421",
      "stream_path": "bk/4"
    },
    {
      "channel_number": 78,
      "name": "dbc news",
      "logo": "http://tvassets.roarzone.info/images/7.png",
      "group": "bangla",
      "url": "https://edge2.roarzone.info:8444/roarzone/bk/7/index.m3u8?token=a0e7db2b332ff9da52510e62076dc48f76048edb-c2e16e3b7804dd4004fc62092d2330f9-1771016021-1771012421",
      "stream_path": "bk/7"
    },
    {
      "channel_number": 81,
      "name": "desh tv",
      "logo": "http://tvassets.roarzone.info/images/9.png",
      "group": "bangla",
      "url": "https://edge2.roarzone.info:8444/roarzone/bk/9/index.m3u8?token=1952a97bb6bd68a1ef16b2089828ccf509bfffbd-488f68b43d93f1b85abaa7420a9742ec-1771016021-1771012421",
      "stream_path": "bk/9"
    },
    {
      "channel_number": 82,
      "name": "duronto tv",
      "logo": "http://tvassets.roarzone.info/images/10.png",
      "group": "bangla",
      "url": "https://edge2.roarzone.info:8444/roarzone/bk/10/index.m3u8?token=4afb65473164e36c53a33cad1718fd0fa4e19f3e-514bc8017de1999b4bfa83f0600a8199-1771016021-1771012421",
      "stream_path": "bk/10"
    },
    {
      "channel_number": 84,
      "name": "maasranga",
      "logo": "http://tvassets.roarzone.info/images/51.png",
      "group": "bangla",
      "url": "https://edge2.roarzone.info:8444/roarzone/bk/51/index.m3u8?token=e9091b968e174019cdc15db5d12244af03355747-bf88b3e7ee999629edcc9d73ec5d3faa-1771016021-1771012421",
      "stream_path": "bk/51"
    },
    {
      "channel_number": 85,
      "name": "mohona tv",
      "logo": "http://tvassets.roarzone.info/images/50.png",
      "group": "bangla",
      "url": "https://edge2.roarzone.info:8444/roarzone/bk/50/index.m3u8?token=43bd40d3580e509b9ac86ca49892b95b3db2ccf3-60c330798655af58d1825cf54e5e24ff-1771016021-1771012421",
      "stream_path": "bk/50"
    },
    {
      "channel_number": 87,
      "name": "my tv",
      "logo": "http://tvassets.roarzone.info/images/56.png",
      "group": "bangla",
      "url": "https://edge2.roarzone.info:8444/roarzone/bk/56/index.m3u8?token=c2daf12479c519d4118206d8195a3aad0479cba7-041e5b2cb145abfb32f3fc3811760137-1771016021-1771012421",
      "stream_path": "bk/56"
    },
    {
      "channel_number": 88,
      "name": "news24",
      "logo": "http://tvassets.roarzone.info/images/18.png",
      "group": "bangla",
      "url": "https://edge2.roarzone.info:8444/roarzone/bk/18/index.m3u8?token=c373c7bac04ee4ed1f43bc73b10db3de51aa3a49-9b9e97042d7a9d512f58d33f3e53ea4f-1771016021-1771012421",
      "stream_path": "bk/18"
    },
    {
      "channel_number": 89,
      "name": "ntv",
      "logo": "http://tvassets.roarzone.info/images/54.png",
      "group": "bangla",
      "url": "https://edge2.roarzone.info:8444/roarzone/bk/54/index.m3u8?token=f9114358be4d85edc3bccec5521ad571c67ee4d0-9700d93ddee9f1c9a07d659b534bc6a2-1771016021-1771012421",
      "stream_path": "bk/54"
    },
    {
      "channel_number": 90,
      "name": "rtv",
      "logo": "http://tvassets.roarzone.info/images/14.png",
      "group": "bangla",
      "url": "https://edge2.roarzone.info:8444/roarzone/bk/14/index.m3u8?token=547c74450b7cb5f5bf8b519afae5735d0681cfb7-5f8af64ef6af4fd35b7f81dc37376f3e-1771016021-1771012421",
      "stream_path": "bk/14"
    },
    {
      "channel_number": 91,
      "name": "sa tv",
      "logo": "http://tvassets.roarzone.info/images/15.png",
      "group": "bangla",
      "url": "https://edge2.roarzone.info:8444/roarzone/bk/15/index.m3u8?token=2eb96d331223ea73f1b8d6206571f62120a23075-5a59b12a0694dfb73146220619a9dbe2-1771016021-1771012421",
      "stream_path": "bk/15"
    },
    {
      "channel_number": 92,
      "name": "sangsad tv",
      "logo": "http://tvassets.roarzone.info/images/88.png",
      "group": "bangla",
      "url": "https://edge2.roarzone.info:8444/roarzone/bk/88/index.m3u8?token=fcf877363d30e95c41c3c3282ca276d874209bbc-3766dd0db46afaaa1790e6d7580210d5-1771016021-1771012421",
      "stream_path": "bk/88"
    },
    {
      "channel_number": 95,
      "name": "star sports 1",
      "logo": "http://tvassets.roarzone.info/images/25.png",
      "group": "sports",
      "url": "https://edge2.roarzone.info:8444/roarzone/edge2/star-sports-1/index.m3u8?token=f53e84ce95f31bebbed27d5ddecb72c057a8fb34-2345a4074da994ebc29186bbf407ea37-1771016021-1771012421",
      "stream_path": "edge2/star-sports-1"
    },
    {
      "channel_number": 96,
      "name": "star sports 2",
      "logo": "http://tvassets.roarzone.info/images/26.png",
      "group": "sports",
      "url": "https://edge2.roarzone.info:8444/roarzone/edge2/star-sports-2/index.m3u8?token=c1b382eeac25c0784da5fd23135b191e3b9014bd-359ec43078edeb425c189567c5ce985b-1771016021-1771012421",
      "stream_path": "edge2/star-sports-2"
    },
    {
      "channel_number": 97,
      "name": "star sports select 1",
      "logo": "http://tvassets.roarzone.info/images/27.png",
      "group": "sports",
      "url": "https://edge2.roarzone.info:8444/roarzone/edge2/star-sports-select-1/index.m3u8?token=5b77d1a0cdafbbbdde12f6eda98ae7189fa54475-4e53f88358f41067e47afbc1f2833e98-1771016021-1771012421",
      "stream_path": "edge2/star-sports-select-1"
    },
    {
      "channel_number": 98,
      "name": "star sports select 2",
      "logo": "http://tvassets.roarzone.info/images/28.png",
      "group": "sports",
      "url": "https://edge2.roarzone.info:8444/roarzone/edge2/star-sports-select-2/index.m3u8?token=b254724061befdfce2480804604e0df2f194cc15-7f87b3def0e34d97431dc0ae462bc853-1771016021-1771012421",
      "stream_path": "edge2/star-sports-select-2"
    },
    {
      "channel_number": 99,
      "name": "atn news",
      "logo": "http://tvassets.roarzone.info/images/49.png",
      "group": "bangla",
      "url": "https://edge2.roarzone.info:8444/roarzone/edge2/atn-news/index.m3u8?token=788c1e0b9e288bc6e80873be52defd993bcee7f5-db0abcdb0f74da70f506e574ed641953-1771016021-1771012421",
      "stream_path": "edge2/atn-news"
    },
    {
      "channel_number": 100,
      "name": "deepto tv",
      "logo": "http://tvassets.roarzone.info/images/8.png",
      "group": "bangla",
      "url": "https://edge2.roarzone.info:8444/roarzone/edge2/deepto_tv/index.m3u8?token=2b1bd1285d147635dcc4cece32b512f75c156c4c-825f3e97cb541eb1191beb60035a1d21-1771016021-1771012421",
      "stream_path": "edge2/deepto_tv"
    },
    {
      "channel_number": 102,
      "name": "somoy tv",
      "logo": "http://tvassets.roarzone.info/images/17.png",
      "group": "bangla",
      "url": "https://edge2.roarzone.info:8444/roarzone/edge3/somoy-tv/index.m3u8?token=9db10de7fa31402eaa14c17ea220e279ea5bccd9-e713e292692c87183015591e7f40c66e-1771016021-1771012421",
      "stream_path": "edge3/somoy-tv"
    },
    {
      "channel_number": 103,
      "name": "ekattor tv",
      "logo": "http://tvassets.roarzone.info/images/11.png",
      "group": "bangla",
      "url": "https://edge2.roarzone.info:8444/roarzone/edge3/ekattor-tv/index.m3u8?token=018cfc14b70cfc8bed4e286c0bcdcdba3b489a84-93ffad57ff8e4e0b4e5f3ca1f5a54c18-1771016021-1771012421",
      "stream_path": "edge3/ekattor-tv"
    },
    {
      "channel_number": 104,
      "name": "ekhon",
      "logo": "http://tvassets.roarzone.info/images/ekhon-tv.jpg",
      "group": "bangla",
      "url": "https://edge2.roarzone.info:8444/roarzone/edge3/ekhon-tv/index.m3u8?token=b39182595ff648d0fb881cb9fe266ebf5cd8ba72-0bce2939f701e4aa4b9db9cb139da4c8-1771016021-1771012421",
      "stream_path": "edge3/ekhon-tv"
    },
    {
      "channel_number": 105,
      "name": "sony max",
      "logo": "http://tvassets.roarzone.info/images/sonymax.png",
      "group": "hindi",
      "url": "https://edge2.roarzone.info:8444/roarzone/edge3/sony-max/index.m3u8?token=e62d4f9b9fba22a1c988e55b0bb9144ece36e629-b56a199e9f5353854df1fd1c4d70d5af-1771016021-1771012421",
      "stream_path": "edge3/sony-max"
    },
    {
      "channel_number": 106,
      "name": "sony max hd",
      "logo": "http://tvassets.roarzone.info/images/sonymaxhd.png",
      "group": "hindi",
      "url": "https://edge2.roarzone.info:8444/roarzone/edge3/sony-max-hd/index.m3u8?token=8a026ca30487a9ee6aa8f3a1b09ab4514a1bfa94-c9347731e1d1d58e0141df6f781cd0cf-1771016021-1771012421",
      "stream_path": "edge3/sony-max-hd"
    },
    {
      "channel_number": 107,
      "name": "sony max 2",
      "logo": "http://tvassets.roarzone.info/images/sonymax2.png",
      "group": "hindi",
      "url": "https://edge2.roarzone.info:8444/roarzone/edge3/sony-max-2/index.m3u8?token=920a0c9a3f4b38afabb176eafa90b3237f82ea31-f906f42362fe296734fd50a387b1b236-1771016021-1771012421",
      "stream_path": "edge3/sony-max-2"
    },
    {
      "channel_number": 108,
      "name": "zee tv",
      "logo": "http://tvassets.roarzone.info/images/40.png",
      "group": "hindi",
      "url": "https://edge2.roarzone.info:8444/roarzone/edge3/zee-tv-hd/index.m3u8?token=e65a9cc983d3efa651ba88fab12d108759cf8b01-4d53161244e1dfede9ee5fbdbbb0e7ea-1771016021-1771012421",
      "stream_path": "edge3/zee-tv-hd"
    },
    {
      "channel_number": 109,
      "name": "zee cinema",
      "logo": "http://tvassets.roarzone.info/images/76.png",
      "group": "hindi",
      "url": "https://edge2.roarzone.info:8444/roarzone/edge3/zee-cinema-hd/index.m3u8?token=b5038b9622602ef082fdb37e82a9cf53df7dd129-93573d320f8b92c81175b0beff668dc6-1771016021-1771012421",
      "stream_path": "edge3/zee-cinema-hd"
    },
    {
      "channel_number": 110,
      "name": "zee bollywood",
      "logo": "http://tvassets.roarzone.info/images/94.png",
      "group": "hindi",
      "url": "https://edge2.roarzone.info:8444/roarzone/edge3/zee-bollywood/index.m3u8?token=420144dd23f0acfd0e216d0912d7cd913a0e82bd-ca3122888b34b1bb0e912d12aa9b6aea-1771016021-1771012421",
      "stream_path": "edge3/zee-bollywood"
    },
    {
      "channel_number": 111,
      "name": "zee-anmol",
      "logo": "http://tvassets.roarzone.info/images/zee-anmol.png",
      "group": "hindi",
      "url": "https://edge2.roarzone.info:8444/roarzone/edge3/zee-anmol/index.m3u8?token=b028e4392dddc286cbd46ef4997134cdf03482e4-33ea4c62ef434c42da7c562fb3acc4b6-1771016021-1771012421",
      "stream_path": "edge3/zee-anmol"
    },
    {
      "channel_number": 112,
      "name": "hum masala",
      "logo": "http://tvassets.roarzone.info/images/hummasala.png",
      "group": "hindi",
      "url": "https://edge2.roarzone.info:8444/roarzone/edge3/hum-masala/index.m3u8?token=4fcaecc140ba4107eef56e5282fd756662725786-cd7c17569e04fa77caf778cab1683178-1771016021-1771012421",
      "stream_path": "edge3/hum-masala"
    },
    {
      "channel_number": 113,
      "name": "hum sitarey",
      "logo": "http://tvassets.roarzone.info/images/humsitarey.png",
      "group": "hindi",
      "url": "https://edge2.roarzone.info:8444/roarzone/edge3/hum-sitaray/index.m3u8?token=aadafbc138c1af90ebc473bdb147188f2b4e44a9-109dadad69e87e4843bc1d45804a56c4-1771016021-1771012421",
      "stream_path": "edge3/hum-sitaray"
    },
    {
      "channel_number": 114,
      "name": "discovery hd",
      "logo": "http://tvassets.roarzone.info/images/43.png",
      "group": "documentary",
      "url": "https://edge2.roarzone.info:8444/roarzone/edge3/discovery-hd/index.m3u8?token=f04dc412dee141203c55e40cfa520293acd1d247-c69b1c5015c3cf8b31754414324b9b38-1771016021-1771012421",
      "stream_path": "edge3/discovery-hd"
    },
    {
      "channel_number": 115,
      "name": "discovery science",
      "logo": "http://tvassets.roarzone.info/images/discoveryscience.png",
      "group": "documentary",
      "url": "https://edge2.roarzone.info:8444/roarzone/edge3/discovery-science/index.m3u8?token=35dbcab82427f6d291c46126013ddec412c3ab95-d451ce4a1d71fc42e183b140f02efced-1771016021-1771012421",
      "stream_path": "edge3/discovery-science"
    },
    {
      "channel_number": 116,
      "name": "discovery turbo",
      "logo": "http://tvassets.roarzone.info/images/discoveryturbo.png",
      "group": "documentary",
      "url": "https://edge2.roarzone.info:8444/roarzone/edge3/discovery-turbo/index.m3u8?token=04f5158305ae3cd308a5aa45bd1375907bf77212-4706b062c7a5a58ea54a7a47db7aca4f-1771016021-1771012421",
      "stream_path": "edge3/discovery-turbo"
    },
    {
      "channel_number": 117,
      "name": "cnn",
      "logo": "http://tvassets.roarzone.info/images/cnn.png",
      "group": "documentary",
      "url": "https://edge2.roarzone.info:8444/roarzone/edge3/cnn/index.m3u8?token=945f08d356f371357f29026cfee84a892162ee19-db446501ac41bde958c9761513f1c49a-1771016021-1771012421",
      "stream_path": "edge3/cnn"
    },
    {
      "channel_number": 118,
      "name": "sony bbc earth hd",
      "logo": "http://tvassets.roarzone.info/images/44.png",
      "group": "documentary",
      "url": "https://edge2.roarzone.info:8444/roarzone/edge3/sony-bbc-earth-hd/index.m3u8?token=673ef8a38251b900e9124088fa4eb0b4852b964c-f2f03a78819f714cb25109fb36db573f-1771016021-1771012421",
      "stream_path": "edge3/sony-bbc-earth-hd"
    },
    {
      "channel_number": 119,
      "name": "animal planet",
      "logo": "http://tvassets.roarzone.info/images/animalplanet.png",
      "group": "documentary",
      "url": "https://edge2.roarzone.info:8444/roarzone/edge3/animal-planet-hd/index.m3u8?token=0b4c9ec07d18242cc46a328f04a9d19d6a067e0b-dd4a607072e52f3ce9d3c61b7d91a848-1771016021-1771012421",
      "stream_path": "edge3/animal-planet-hd"
    },
    {
      "channel_number": 120,
      "name": "zee bangla",
      "logo": "http://tvassets.roarzone.info/images/34.png",
      "group": "inbangla",
      "url": "https://edge2.roarzone.info:8444/roarzone/edge3/zee-bangla/index.m3u8?token=ac888e12411aca151d35a996c7bb998d8b368a63-b0fbe130f5d5b6562b47e7362be0c7ce-1771016021-1771012421",
      "stream_path": "edge3/zee-bangla"
    },
    {
      "channel_number": 121,
      "name": "zee bangla cinema",
      "logo": "http://tvassets.roarzone.info/images/29.png",
      "group": "inbangla",
      "url": "https://edge2.roarzone.info:8444/roarzone/edge3/zee-bangla-cinema/index.m3u8?token=74f562a1b03d7c82bf812c4116b7d15d680a7488-faa11517a416268ba98a85475b3a1288-1771016021-1771012421",
      "stream_path": "edge3/zee-bangla-cinema"
    },
    {
      "channel_number": 122,
      "name": "sony aath",
      "logo": "http://tvassets.roarzone.info/images/33.png",
      "group": "inbangla",
      "url": "https://edge2.roarzone.info:8444/roarzone/edge3/sony-aath/index.m3u8?token=639acab998cbeb8dc4a9e468d1ba05c51961af7e-43baae8fec5b96fc0096b9faca783209-1771016021-1771012421",
      "stream_path": "edge3/sony-aath"
    },
    {
      "channel_number": 123,
      "name": "cartoon network hd",
      "logo": "http://tvassets.roarzone.info/images/cartoon-network-hd.webp",
      "group": "kids",
      "url": "https://edge2.roarzone.info:8444/roarzone/edge3/cartoon-network-hd/index.m3u8?token=125cf5d2e3a33d9e3cfd0f7c897d67d837cd3ed3-1f73d7d3fbb1e72d82fa8ae655778bd5-1771016021-1771012421",
      "stream_path": "edge3/cartoon-network-hd"
    },
    {
      "channel_number": 124,
      "name": "discovery kids",
      "logo": "http://tvassets.roarzone.info/images/discoverykids.png",
      "group": "kids",
      "url": "https://edge2.roarzone.info:8444/roarzone/edge3/discovery-kids/index.m3u8?token=c2d15efc6447049c2fca188039919f1c20464a6b-c35908730ed9cd92c93a01cd15163534-1771016021-1771012421",
      "stream_path": "edge3/discovery-kids"
    },
    {
      "channel_number": 125,
      "name": "sony yay",
      "logo": "http://tvassets.roarzone.info/images/sonyyay.png",
      "group": "kids",
      "url": "https://edge2.roarzone.info:8444/roarzone/edge3/sony-yay/index.m3u8?token=6b8d140e35c38500b32b4847addf04e81fe12eba-b51ae37763c4c6a4d3b0dfa54e09646e-1771016021-1771012421",
      "stream_path": "edge3/sony-yay"
    },
    {
      "channel_number": 126,
      "name": "tlc hd",
      "logo": "http://tvassets.roarzone.info/images/tlc-hd.webp",
      "group": "english",
      "url": "https://edge2.roarzone.info:8444/roarzone/edge3/tlc-hd/index.m3u8?token=926986a3b0f3b0948bfece93539b37f33e443aa7-e88fb51716688e2f02811edb03b0d463-1771016021-1771012421",
      "stream_path": "edge3/tlc-hd"
    },
    {
      "channel_number": 127,
      "name": "b4u music",
      "logo": "http://tvassets.roarzone.info/images/b4umusic.png",
      "group": "music",
      "url": "https://edge2.roarzone.info:8444/roarzone/edge3/b4u-music/index.m3u8?token=1882e20be7e977521fe504ace060e3a8bf8c1614-d05924b2ee88695d083210053d162a58-1771016021-1771012421",
      "stream_path": "edge3/b4u-music"
    },
    {
      "channel_number": 128,
      "name": "jamuna tv",
      "logo": "http://tvassets.roarzone.info/images/13.png",
      "group": "bangla",
      "url": "https://edge2.roarzone.info:8444/roarzone/edge3/jamuna-tv/index.m3u8?token=bb0dd2cb0a9e5758fea0a4b2646a0cddf38352f8-566824487505101f7c16b64bd36a3f60-1771016021-1771012421",
      "stream_path": "edge3/jamuna-tv"
    },
    {
      "channel_number": 129,
      "name": "channel s",
      "logo": "http://tvassets.roarzone.info/images/channel-s.png",
      "group": "bangla",
      "url": "https://edge2.roarzone.info:8444/roarzone/edge3/channel-s/index.m3u8?token=9360d4b2aea2d8feb212059e851d42b1c908474e-c3cc6dfedb7eefc22e46aa290817f62a-1771016021-1771012421",
      "stream_path": "edge3/channel-s"
    },
    {
      "channel_number": 130,
      "name": "global tv",
      "logo": "http://tvassets.roarzone.info/images/global-tv.png",
      "group": "bangla",
      "url": "https://edge2.roarzone.info:8444/roarzone/edge3/global-tv/index.m3u8?token=a8d3c25651283dc13518d3fe395025bcc8bc225a-4f85ecbdcb48b30390b313ff4c8f9dad-1771016021-1771012421",
      "stream_path": "edge3/global-tv"
    },
    {
      "channel_number": 131,
      "name": "ananda tv",
      "logo": "http://tvassets.roarzone.info/images/16.png",
      "group": "bangla",
      "url": "https://edge2.roarzone.info:8444/roarzone/edge3/ananda-tv/index.m3u8?token=cde04dabf92ceddf93a3f86edfcac6258e56cbaa-7e3f4896c66f191df21c0f78e7ee5fee-1771016021-1771012421",
      "stream_path": "edge3/ananda-tv"
    },
    {
      "channel_number": 132,
      "name": "bangla tv",
      "logo": "http://tvassets.roarzone.info/images/19.png",
      "group": "bangla",
      "url": "https://edge2.roarzone.info:8444/roarzone/edge3/bangla-tv/index.m3u8?token=7d27822e2ffb61f8d23710a959d67fe929f77804-c8ffbb50cf049bd67ee705ca4a2aa6f5-1771016021-1771012421",
      "stream_path": "edge3/bangla-tv"
    },
    {
      "channel_number": 133,
      "name": "channel i",
      "logo": "http://tvassets.roarzone.info/images/6.png",
      "group": "bangla",
      "url": "https://edge2.roarzone.info:8444/roarzone/edge3/channel-i/index.m3u8?token=7e0c4318b1d324265962c5fcaa6d881b5b1201ad-8447791ed6a62849737d513a31dc3917-1771016021-1771012421",
      "stream_path": "edge3/channel-i"
    },
    {
      "channel_number": 134,
      "name": "independent tv",
      "logo": "http://tvassets.roarzone.info/images/12.png",
      "group": "bangla",
      "url": "https://edge2.roarzone.info:8444/roarzone/edge3/independent-tv/index.m3u8?token=2de4c4f6a83a75450db83b7e269fa157475bff6a-e0f2ee151ca39fdee9be4a06c24ab2f8-1771016021-1771012421",
      "stream_path": "edge3/independent-tv"
    },
    {
      "channel_number": 135,
      "name": "movie bangla tv",
      "logo": "http://tvassets.roarzone.info/images/86.png",
      "group": "bangla",
      "url": "https://edge2.roarzone.info:8444/roarzone/edge3/movie-bangla/index.m3u8?token=ea1d718cd9599fb1d12131059463755f34f2dfe7-9aca37a1eaa3729973faa6ff12b91575-1771016021-1771012421",
      "stream_path": "edge3/movie-bangla"
    },
    {
      "channel_number": 136,
      "name": "bijoy-tv",
      "logo": "http://tvassets.roarzone.info/images/bijoy-tv.jpg",
      "group": "bangla",
      "url": "https://edge2.roarzone.info:8444/roarzone/edge3/bijoy-tv/index.m3u8?token=766793a5f025d8e4df5d9bff23caba74a8d3fa5b-90e39a39326dbe86082ce21fe8c062d2-1771016021-1771012421",
      "stream_path": "edge3/bijoy-tv"
    },
    {
      "channel_number": 137,
      "name": "sony tv",
      "logo": "http://tvassets.roarzone.info/images/38.png",
      "group": "hindi",
      "url": "https://edge2.roarzone.info:8444/roarzone/edge3/sony-entertainment-television-hd/index.m3u8?token=a15cbb8e1ad47c840df87d7ae91cc99b522789d1-ab528f3b74913a58d05b71756e745945-1771016021-1771012421",
      "stream_path": "edge3/sony-entertainment-television-hd"
    },
    {
      "channel_number": 138,
      "name": "and pictures",
      "logo": "http://tvassets.roarzone.info/images/100.png",
      "group": "hindi",
      "url": "https://edge2.roarzone.info:8444/roarzone/edge3/pictures-hd/index.m3u8?token=35c686013add518ebe25a58ce9579a5231006507-b7d7bc075604572a3d3f00505f28cd8d-1771016021-1771012421",
      "stream_path": "edge3/pictures-hd"
    },
    {
      "channel_number": 139,
      "name": "hum tv",
      "logo": "http://tvassets.roarzone.info/images/humtv.png",
      "group": "hindi",
      "url": "https://edge2.roarzone.info:8444/roarzone/edge3/hum/index.m3u8?token=ee0b0abecfaef3dfea6b2d9420bd52db1745418d-93dade9d03928124e2acc5277764f118-1771016021-1771012421",
      "stream_path": "edge3/hum"
    },
    {
      "channel_number": 140,
      "name": "b4u movies",
      "logo": "http://tvassets.roarzone.info/images/b4umovies.png",
      "group": "hindi",
      "url": "https://edge2.roarzone.info:8444/roarzone/edge3/b4u-movies-apac/index.m3u8?token=37887fc2278a07b44ad54195550b110428745a13-88ea8f4f1666c25fd25e92784348867e-1771016021-1771012421",
      "stream_path": "edge3/b4u-movies-apac"
    },
    {
      "channel_number": 141,
      "name": "sony sab",
      "logo": "http://tvassets.roarzone.info/images/36.png",
      "group": "hindi",
      "url": "https://edge2.roarzone.info:8444/roarzone/edge3/sony-sab-hd/index.m3u8?token=279a844661d1d4a875d6d18e1d2e5f3f2b847fd7-d12b4b6daad8f65f3ea84521e9c1fbb6-1771016021-1771012421",
      "stream_path": "edge3/sony-sab-hd"
    },
    {
      "channel_number": 142,
      "name": "discovery hd investigation",
      "logo": "http://tvassets.roarzone.info/images/discoveryhdInvestigation.png",
      "group": "documentary",
      "url": "https://edge2.roarzone.info:8444/roarzone/edge3/investigation-discovery-hd/index.m3u8?token=b62851699e8755bac85e0f6225d746b1900a4534-ffd52f639a9e64934e45184aab3d3637-1771016021-1771012421",
      "stream_path": "edge3/investigation-discovery-hd"
    },
    {
      "channel_number": 143,
      "name": "cartoon network",
      "logo": "http://tvassets.roarzone.info/images/cartoon-network.webp",
      "group": "kids",
      "url": "https://edge2.roarzone.info:8444/roarzone/edge3/cartoon-network/index.m3u8?token=6f7ac43d049aa6f688f074bc68121153f6872d30-fda0a6bd2598272b75de98a63d32c9b5-1771016021-1771012421",
      "stream_path": "edge3/cartoon-network"
    },
    {
      "channel_number": 144,
      "name": "pogo",
      "logo": "http://tvassets.roarzone.info/images/pogo.png",
      "group": "kids",
      "url": "https://edge2.roarzone.info:8444/roarzone/edge3/pogo/index.m3u8?token=8b8ac96e9332e2b621fe41f6209c91fdac1f29da-f026929337ed3037114c2b3eca58aa62-1771016021-1771012421",
      "stream_path": "edge3/pogo"
    },
    {
      "channel_number": 145,
      "name": "zee cafe hd",
      "logo": "http://tvassets.roarzone.info/images/69.png",
      "group": "english",
      "url": "https://edge2.roarzone.info:8444/roarzone/edge3/zee-cafe/index.m3u8?token=1feeb17c4d8f11ccc590c1c5da7d79241f3ecd7c-f7e0d7a2155e93afc931f8145d5b60cb-1771016021-1771012421",
      "stream_path": "edge3/zee-cafe"
    },
    {
      "channel_number": 146,
      "name": "sony pix",
      "logo": "http://tvassets.roarzone.info/images/41.png",
      "group": "english",
      "url": "https://edge2.roarzone.info:8444/roarzone/edge3/sony-pix-hd/index.m3u8?token=d1204fe51ab5b44060a910cab1aec7fa4a96a288-634c2ccfe35edceef109d0d63aca8f31-1771016021-1771012421",
      "stream_path": "edge3/sony-pix-hd"
    },
    {
      "channel_number": 147,
      "name": "zing",
      "logo": "http://tvassets.roarzone.info/images/93.png",
      "group": "music",
      "url": "https://edge2.roarzone.info:8444/roarzone/edge3/zing/index.m3u8?token=66cf9a4c97b6a785b1ac42034b394d5404563965-747e3007952086c358d23ba32148aa76-1771016021-1771012421",
      "stream_path": "edge3/zing"
    },
    {
      "channel_number": 148,
      "name": "asian tv",
      "logo": "http://tvassets.roarzone.info/images/62.png",
      "group": "bangla",
      "url": "https://edge2.roarzone.info:8444/roarzone/edge3/asian-tv/index.m3u8?token=c2014b35875630c5c401eafc30d75953cf4a2591-a9b73541b71321361dd3c4cca7406891-1771016021-1771012421",
      "stream_path": "edge3/asian-tv"
    },
    {
      "channel_number": 149,
      "name": "euro sports",
      "logo": "http://tvassets.roarzone.info/images/euro_sports_hd.png",
      "group": "sports",
      "url": "https://edge2.roarzone.info:8444/roarzone/edge3/euro-sport-hd/index.m3u8?token=2c48afc9b7bffabf5282788c7b22009ef5fa453a-316b24f352afc25ccb09d7fa8b6e4014-1771016021-1771012421",
      "stream_path": "edge3/euro-sport-hd"
    },
    {
      "channel_number": 150,
      "name": "ten cricket",
      "logo": "http://tvassets.roarzone.info/images/ten_cricket.png",
      "group": "sports",
      "url": "https://edge2.roarzone.info:8444/roarzone/edge3/sony-ten-cricket/index.m3u8?token=e6b780bd16d8a15fd665b6eaadb8c315a918a45b-4d82b063b18c254f0ec97674bc5ee5c0-1771016021-1771012421",
      "stream_path": "edge3/sony-ten-cricket"
    },
    {
      "channel_number": 151,
      "name": "zee action",
      "logo": "http://tvassets.roarzone.info/images/90.png",
      "group": "hindi",
      "url": "https://edge2.roarzone.info:8444/roarzone/edge3/zee-action/index.m3u8?token=4afe3d6300cb0c5d36c821dd9c76a9b02d4128ab-2509c1f5ba71198c7e015447e7ac247a-1771016021-1771012421",
      "stream_path": "edge3/zee-action"
    },
    {
      "channel_number": 152,
      "name": "and tv hd",
      "logo": "http://tvassets.roarzone.info/images/74.png",
      "group": "hindi",
      "url": "https://edge2.roarzone.info:8444/roarzone/edge3/tv-hd/index.m3u8?token=074f5e21dc417b212d5e231f4abab191cc7f6179-610db08dbcf4377451915d4656d60385-1771016021-1771012421",
      "stream_path": "edge3/tv-hd"
    },
    {
      "channel_number": 153,
      "name": "banglavision tv",
      "logo": "http://tvassets.roarzone.info/images/3.png",
      "group": "bangla",
      "url": "https://edge2.roarzone.info:8444/roarzone/edge2/banglavision/index.m3u8?token=dbd574aa132e7f5064b69a9e3fb2b0c0a0c6f9cc-c3ad28b0f7e8fbc2984c6d3a3c54089e-1771016021-1771012421",
      "stream_path": "edge2/banglavision"
    }
  ]
}