{
  "generated_at": "Sat Feb 14 09:48:34 2026",
  "channels": [
    {
      "channel_number": 1,
      "name": "t sports",
      "logo": "http://tvassets.roarzone.info/images/102.png",
      "group": "sports",
      "url": "https://edge2.roarzone.info:8444/roarzone/edge2/tsports/index.m3u8?token=92c7e25636b3820842c007e1da162e68a01f4b65-f64e30d0d2a93e9f3c99d829e3a5e877-1771066008-1771062408",
      "stream_path": "edge2/tsports"
    },
    {
      "channel_number": 8,
      "name": "sony ten 1",
      "logo": "http://tvassets.roarzone.info/images/20.png",
      "group": "sports",
      "url": "https://edge2.roarzone.info:8444/roarzone/edge2/sony-sports-1-hd/index.m3u8?token=179d9b86f3c18bbb072af5c4a3fe1b023ca536e0-7ef8f00c981d57b435e844a930d929a0-1771066009-1771062409",
      "stream_path": "edge2/sony-sports-1-hd"
    },
    {
      "channel_number": 9,
      "name": "sony ten 2",
      "logo": "http://tvassets.roarzone.info/images/21.png",
      "group": "sports",
      "url": "https://edge2.roarzone.info:8444/roarzone/edge2/sony-sports-2-hd/index.m3u8?token=3c4e31ef2be49a9aa34e3c33df4ca1aa610437a0-0c74334e110d3c30b5f20f0824d3c3f4-1771066009-1771062409",
      "stream_path": "edge2/sony-sports-2-hd"
    },
    {
      "channel_number": 10,
      "name": "sony ten 3",
      "logo": "http://tvassets.roarzone.info/images/22.png",
      "group": "sports",
      "url": "https://edge2.roarzone.info:8444/roarzone/edge2/sony-sports-3-hd/index.m3u8?token=c1fd55f870bb44425b1ad162cbca5b3528d124c2-8f93c4c9531f3cf3a90516d3b719a1a2-1771066009-1771062409",
      "stream_path": "edge2/sony-sports-3-hd"
    },
    {
      "channel_number": 11,
      "name": "sony six",
      "logo": "http://tvassets.roarzone.info/images/24.png",
      "group": "sports",
      "url": "https://edge2.roarzone.info:8444/roarzone/edge2/sony-sports-5-hd/index.m3u8?token=a853409eb38886d76f3e18122fa6a8ea66a14164-47b1a4fbb50b503577cda9d2625f0093-1771066009-1771062409",
      "stream_path": "edge2/sony-sports-5-hd"
    },
    {
      "channel_number": 15,
      "name": "dubai sports",
      "logo": "http://tvassets.roarzone.info/images/dubai-sports.png",
      "group": "sports",
      "url": "https://edge2.roarzone.info:8444/roarzone/bk/dubai-sports/index.m3u8?token=74abe8643c9d55e478acc448a86a631ee3253bd0-0259e14cea285859a5c587693091b47a-1771066009-1771062409",
      "stream_path": "bk/dubai-sports"
    },
    {
      "channel_number": 21,
      "name": "colors",
      "logo": "http://tvassets.roarzone.info/images/68.png",
      "group": "hindi",
      "url": "https://edge2.roarzone.info:8444/roarzone/bk/68/index.m3u8?token=c1215a005f8bb10a3e137454ccfa3d0e9dbd5ee5-f6798a557d23f716ebabdfacea3c1c47-1771066009-1771062409",
      "stream_path": "bk/68"
    },
    {
      "channel_number": 27,
      "name": "star plus",
      "logo": "http://tvassets.roarzone.info/images/67.png",
      "group": "hindi",
      "url": "https://edge2.roarzone.info:8444/roarzone/bk/67/index.m3u8?token=e3f9a0ebaf67a5f989c30641c2adef444d7322dc-5d7c82937a678545d0ff9c9378243d6c-1771066009-1771062409",
      "stream_path": "bk/67"
    },
    {
      "channel_number": 41,
      "name": "natgeo",
      "logo": "http://tvassets.roarzone.info/images/35.png",
      "group": "documentary",
      "url": "https://edge2.roarzone.info:8444/roarzone/bk/35/index.m3u8?token=70e9b45b22385ed9474c3157c33084b6254123be-2c99d583a3b93ba54164679fc30027b5-1771066009-1771062409",
      "stream_path": "bk/35"
    },
    {
      "channel_number": 43,
      "name": "star jalsha",
      "logo": "http://tvassets.roarzone.info/images/30.png",
      "group": "inbangla",
      "url": "https://edge2.roarzone.info:8444/roarzone/bk/30/index.m3u8?token=0d047f778451ad43d86dfd8501b64f02bd6caae7-61e6a0d7ceb4f18a17d598a3fe7e947e-1771066009-1771062409",
      "stream_path": "bk/30"
    },
    {
      "channel_number": 44,
      "name": "star jalsha movies",
      "logo": "http://tvassets.roarzone.info/images/31.png",
      "group": "inbangla",
      "url": "https://edge2.roarzone.info:8444/roarzone/bk/31/index.m3u8?token=8c2783f1fbc69c99c141a2071ebe03dcc290b35d-796d73e50a85f67abb4db0bb49c27f21-1771066009-1771062409",
      "stream_path": "bk/31"
    },
    {
      "channel_number": 47,
      "name": "colors bangla",
      "logo": "http://tvassets.roarzone.info/images/66.png",
      "group": "inbangla",
      "url": "https://edge2.roarzone.info:8444/roarzone/bk/66/index.m3u8?token=78558a52f1f366132921c6820b58981779e7f875-b7347a41d5fd1dc4e9accf423402d584-1771066009-1771062409",
      "stream_path": "bk/66"
    },
    {
      "channel_number": 50,
      "name": "nick",
      "logo": "http://tvassets.roarzone.info/images/55.png",
      "group": "kids",
      "url": "https://edge2.roarzone.info:8444/roarzone/bk/55/index.m3u8?token=919f290749eba0be453fda253c08a934cdde4b68-4570c348735344aafa269bb0e50639ff-1771066009-1771062409",
      "stream_path": "bk/55"
    },
    {
      "channel_number": 54,
      "name": "star movies",
      "logo": "http://tvassets.roarzone.info/images/starmovies.png",
      "group": "english",
      "url": "https://edge2.roarzone.info:8444/roarzone/bk/starmovies/index.m3u8?token=55a94005fafe00af681dc85defb90d659f9f05f6-a43c7c82fd7e015302dd443c2d6f6bf0-1771066009-1771062409",
      "stream_path": "bk/starmovies"
    },
    {
      "channel_number": 57,
      "name": "dw news",
      "logo": "http://tvassets.roarzone.info/images/85.png",
      "group": "english",
      "url": "https://edge2.roarzone.info:8444/roarzone/bk/85/index.m3u8?token=178d71de3b2accb16f97704d38322d7e62711ee3-3468ee1a0138f2e491cefc2dbfc1b4d9-1771066009-1771062409",
      "stream_path": "bk/85"
    },
    {
      "channel_number": 58,
      "name": "al jazeera",
      "logo": "http://tvassets.roarzone.info/images/89.png",
      "group": "english",
      "url": "https://edge2.roarzone.info:8444/roarzone/bk/89/index.m3u8?token=f31f4f4fe9a1736dcbb3f1af5158b93623bbf060-233dbb8a3d34bd66cf26e714148f381f-1771066009-1771062409",
      "stream_path": "bk/89"
    },
    {
      "channel_number": 59,
      "name": "gaan bangla",
      "logo": "http://tvassets.roarzone.info/images/58.png",
      "group": "music",
      "url": "https://edge2.roarzone.info:8444/roarzone/bk/58/index.m3u8?token=a8227b930cc6e8758e8e57566c296b4371051380-f2de4da09b8dd8f5a9d6a9af76a66313-1771066009-1771062409",
      "stream_path": "bk/58"
    },
    {
      "channel_number": 60,
      "name": "9xm",
      "logo": "http://tvassets.roarzone.info/images/48.png",
      "group": "music",
      "url": "https://edge2.roarzone.info:8444/roarzone/bk/48/index.m3u8?token=4e91d2d1329932a82f6a3d1ad1e769c5978b8259-ac0aa4849c016c75075d03ce2eb3db85-1771066009-1771062409",
      "stream_path": "bk/48"
    },
    {
      "channel_number": 64,
      "name": "nagorik tv",
      "logo": "http://tvassets.roarzone.info/images/59.png",
      "group": "bangla",
      "url": "https://edge2.roarzone.info:8444/roarzone/edge2/nagorik/index.m3u8?token=de0188f207ed10f0791ad7f6acda7ffdc2fccf12-08b79a4b2c5c2c27a8a9094768a1c9fb-1771066009-1771062409",
      "stream_path": "edge2/nagorik"
    },
    {
      "channel_number": 65,
      "name": "channel 24",
      "logo": "http://tvassets.roarzone.info/images/5.png",
      "group": "bangla",
      "url": "https://edge2.roarzone.info:8444/roarzone/edge2/channel24/index.m3u8?token=2f2f42b3880fc67f743382ff25464d6f7ad1afa0-64adf8930f3b748b0c6bf8c901c72c2d-1771066009-1771062409",
      "stream_path": "edge2/channel24"
    },
    {
      "channel_number": 67,
      "name": "ekushy tv",
      "logo": "http://tvassets.roarzone.info/images/65.png",
      "group": "bangla",
      "url": "https://edge2.roarzone.info:8444/roarzone/bk/65/index.m3u8?token=8ca93e8eb19c7afdee177e2051b991856e412977-63718d3f303f576f67f1e6152c84f1bd-1771066009-1771062409",
      "stream_path": "bk/65"
    },
    {
      "channel_number": 69,
      "name": "atn bangla",
      "logo": "http://tvassets.roarzone.info/images/2.png",
      "group": "bangla",
      "url": "https://edge2.roarzone.info:8444/roarzone/bk/2/index.m3u8?token=8fab43fe276643f880b5ad1416c57ac726085beb-5f0c5bd4d9203fd16fd75140c5226500-1771066009-1771062409",
      "stream_path": "bk/2"
    },
    {
      "channel_number": 73,
      "name": "boishakhi tv",
      "logo": "http://tvassets.roarzone.info/images/61.png",
      "group": "bangla",
      "url": "https://edge2.roarzone.info:8444/roarzone/bk/61/index.m3u8?token=4dab05ea28573ff790ce6f8f8fab523ea97bb038-d9dacf2ca0ea35f607af68b689bc85f1-1771066009-1771062409",
      "stream_path": "bk/61"
    },
    {
      "channel_number": 74,
      "name": "btv",
      "logo": "http://tvassets.roarzone.info/images/53.png",
      "group": "bangla",
      "url": "https://edge2.roarzone.info:8444/roarzone/bk/53/index.m3u8?token=707914ce6c7c0efb3f785d1a015491125fe13abe-01b48c8de9e929fd4081c6fc7865b56b-1771066009-1771062409",
      "stream_path": "bk/53"
    },
    {
      "channel_number": 75,
      "name": "btv world",
      "logo": "http://tvassets.roarzone.info/images/84.png",
      "group": "bangla",
      "url": "https://edge2.roarzone.info:8444/roarzone/bk/84/index.m3u8?token=7f3fd122d4dc579d22768002608c1ddf648bb89d-7aac9f8340e51cca78d2e54f265d171d-1771066009-1771062409",
      "stream_path": "bk/84"
    },
    {
      "channel_number": 76,
      "name": "channel 9",
      "logo": "http://tvassets.roarzone.info/images/4.png",
      "group": "bangla",
      "url": "https://edge2.roarzone.info:8444/roarzone/bk/4/index.m3u8?token=8853190419b5ebd61728a862e6ab3d263c0f7969-3bcef5fbe5bb065c74a791d1c2abc60d-1771066009-1771062409",
      "stream_path": "bk/4"
    },
    {
      "channel_number": 78,
      "name": "dbc news",
      "logo": "http://tvassets.roarzone.info/images/7.png",
      "group": "bangla",
      "url": "https://edge2.roarzone.info:8444/roarzone/bk/7/index.m3u8?token=412cfb3008a82ac2b89cfa74b9a6478a498973dd-6da1e1d27c53899175e5f709384b412a-1771066009-1771062409",
      "stream_path": "bk/7"
    },
    {
      "channel_number": 81,
      "name": "desh tv",
      "logo": "http://tvassets.roarzone.info/images/9.png",
      "group": "bangla",
      "url": "https://edge2.roarzone.info:8444/roarzone/bk/9/index.m3u8?token=80ef70ef9048981aa34ce87b728c3c5bc2108e75-3017967aac5d74db8042557200ebb3dd-1771066009-1771062409",
      "stream_path": "bk/9"
    },
    {
      "channel_number": 82,
      "name": "duronto tv",
      "logo": "http://tvassets.roarzone.info/images/10.png",
      "group": "bangla",
      "url": "https://edge2.roarzone.info:8444/roarzone/bk/10/index.m3u8?token=a1a82ac77c67b031012512fc69c6be689acf7aaa-4e883b6e238e4d4f6410482802e98bda-1771066009-1771062409",
      "stream_path": "bk/10"
    },
    {
      "channel_number": 84,
      "name": "maasranga",
      "logo": "http://tvassets.roarzone.info/images/51.png",
      "group": "bangla",
      "url": "https://edge2.roarzone.info:8444/roarzone/bk/51/index.m3u8?token=7418f947e47244bef9077e87cb8f72cc56fcba3a-eac88a860b7c783bfa706b681be8649d-1771066009-1771062409",
      "stream_path": "bk/51"
    },
    {
      "channel_number": 85,
      "name": "mohona tv",
      "logo": "http://tvassets.roarzone.info/images/50.png",
      "group": "bangla",
      "url": "https://edge2.roarzone.info:8444/roarzone/bk/50/index.m3u8?token=f6ac7db49c7c19a0b42ef0b60445e5d42acd6181-2c85f41d433902e3f4248747f8338c2b-1771066009-1771062409",
      "stream_path": "bk/50"
    },
    {
      "channel_number": 87,
      "name": "my tv",
      "logo": "http://tvassets.roarzone.info/images/56.png",
      "group": "bangla",
      "url": "https://edge2.roarzone.info:8444/roarzone/bk/56/index.m3u8?token=0549c8df2598ca16db7ba81b2c9190bbfbbdc96f-1a7cec4810db2719eb6d131c3aff8be8-1771066009-1771062409",
      "stream_path": "bk/56"
    },
    {
      "channel_number": 88,
      "name": "news24",
      "logo": "http://tvassets.roarzone.info/images/18.png",
      "group": "bangla",
      "url": "https://edge2.roarzone.info:8444/roarzone/bk/18/index.m3u8?token=31ee0721dd7dee7de2da5c87f46e421c37a2c6f0-974e79cfdf0b8d60cdfd458c3eda3bdd-1771066009-1771062409",
      "stream_path": "bk/18"
    },
    {
      "channel_number": 89,
      "name": "ntv",
      "logo": "http://tvassets.roarzone.info/images/54.png",
      "group": "bangla",
      "url": "https://edge2.roarzone.info:8444/roarzone/bk/54/index.m3u8?token=8297d76ceb479195ddfdd90a14055b582a62d085-8b274a46cbb0410a457c30f1d563dd34-1771066009-1771062409",
      "stream_path": "bk/54"
    },
    {
      "channel_number": 90,
      "name": "rtv",
      "logo": "http://tvassets.roarzone.info/images/14.png",
      "group": "bangla",
      "url": "https://edge2.roarzone.info:8444/roarzone/bk/14/index.m3u8?token=f6d66273778db0c3db95e935c82396ef9505c922-596eecad37cfa45381835124d7f68520-1771066009-1771062409",
      "stream_path": "bk/14"
    },
    {
      "channel_number": 91,
      "name": "sa tv",
      "logo": "http://tvassets.roarzone.info/images/15.png",
      "group": "bangla",
      "url": "https://edge2.roarzone.info:8444/roarzone/bk/15/index.m3u8?token=7ff9b31a675e8033fc39a1e9d3a0874cae226101-7eed722a2a693ae38145198728a9e502-1771066009-1771062409",
      "stream_path": "bk/15"
    },
    {
      "channel_number": 92,
      "name": "sangsad tv",
      "logo": "http://tvassets.roarzone.info/images/88.png",
      "group": "bangla",
      "url": "https://edge2.roarzone.info:8444/roarzone/bk/88/index.m3u8?token=aead49f3d7e60541fcc3b2c65c9f9cd625b28a83-7c0ebf1c8726d11f5e32effe5c891401-1771066009-1771062409",
      "stream_path": "bk/88"
    },
    {
      "channel_number": 95,
      "name": "star sports 1",
      "logo": "http://tvassets.roarzone.info/images/25.png",
      "group": "sports",
      "url": "https://edge2.roarzone.info:8444/roarzone/edge2/star-sports-1/index.m3u8?token=b77da023ea0affe422da0fd14078b84965d4aed4-8b34c0a8d26720360fd604fd9946d15c-1771066009-1771062409",
      "stream_path": "edge2/star-sports-1"
    },
    {
      "channel_number": 96,
      "name": "star sports 2",
      "logo": "http://tvassets.roarzone.info/images/26.png",
      "group": "sports",
      "url": "https://edge2.roarzone.info:8444/roarzone/edge2/star-sports-2/index.m3u8?token=07b1f4d682e512f12efdd68aa659595f9df69e28-12f67826d574641a5c054c21c1b56afe-1771066009-1771062409",
      "stream_path": "edge2/star-sports-2"
    },
    {
      "channel_number": 97,
      "name": "star sports select 1",
      "logo": "http://tvassets.roarzone.info/images/27.png",
      "group": "sports",
      "url": "https://edge2.roarzone.info:8444/roarzone/edge2/star-sports-select-1/index.m3u8?token=b9af3be09a75d9f078294c57819a06b8c8a3a76f-520099ac525385b6267f59ef450dff7f-1771066009-1771062409",
      "stream_path": "edge2/star-sports-select-1"
    },
    {
      "channel_number": 98,
      "name": "star sports select 2",
      "logo": "http://tvassets.roarzone.info/images/28.png",
      "group": "sports",
      "url": "https://edge2.roarzone.info:8444/roarzone/edge2/star-sports-select-2/index.m3u8?token=c4d6f8672db22f720f7e68eb67c558a9fa97c591-b5676394a3bfc1d6d220692360ef5ccd-1771066009-1771062409",
      "stream_path": "edge2/star-sports-select-2"
    },
    {
      "channel_number": 99,
      "name": "atn news",
      "logo": "http://tvassets.roarzone.info/images/49.png",
      "group": "bangla",
      "url": "https://edge2.roarzone.info:8444/roarzone/edge2/atn-news/index.m3u8?token=a29432d1fbde4273111c544043d3b6c7b1032058-693197b6679f1f7d5a2a06fb2d516844-1771066009-1771062409",
      "stream_path": "edge2/atn-news"
    },
    {
      "channel_number": 100,
      "name": "deepto tv",
      "logo": "http://tvassets.roarzone.info/images/8.png",
      "group": "bangla",
      "url": "https://edge2.roarzone.info:8444/roarzone/edge2/deepto_tv/index.m3u8?token=6fea9d66d602beda4bdad22533ecea11d0bccff9-b51f085f0f8f2100a332b7a2bb8ffec2-1771066009-1771062409",
      "stream_path": "edge2/deepto_tv"
    },
    {
      "channel_number": 102,
      "name": "somoy tv",
      "logo": "http://tvassets.roarzone.info/images/17.png",
      "group": "bangla",
      "url": "https://edge2.roarzone.info:8444/roarzone/edge3/somoy-tv/index.m3u8?token=b330ec24961092fc2eec9f9b72d7487863ec1275-9434ebdaaf18459de6adb8910f53ef2d-1771066009-1771062409",
      "stream_path": "edge3/somoy-tv"
    },
    {
      "channel_number": 103,
      "name": "ekattor tv",
      "logo": "http://tvassets.roarzone.info/images/11.png",
      "group": "bangla",
      "url": "https://edge2.roarzone.info:8444/roarzone/edge3/ekattor-tv/index.m3u8?token=33c24046aa5d0e54981242b9745203cacae6ca04-24e69b4db4dd8eb2da3ceb29e4b7d74b-1771066009-1771062409",
      "stream_path": "edge3/ekattor-tv"
    },
    {
      "channel_number": 104,
      "name": "ekhon",
      "logo": "http://tvassets.roarzone.info/images/ekhon-tv.jpg",
      "group": "bangla",
      "url": "https://edge2.roarzone.info:8444/roarzone/edge3/ekhon-tv/index.m3u8?token=22c8f5b9e088469952db41fff94b82776b909255-891ae0cd44a5a8cb91b4e400d44e0d7a-1771066009-1771062409",
      "stream_path": "edge3/ekhon-tv"
    },
    {
      "channel_number": 105,
      "name": "sony max",
      "logo": "http://tvassets.roarzone.info/images/sonymax.png",
      "group": "hindi",
      "url": "https://edge2.roarzone.info:8444/roarzone/edge3/sony-max/index.m3u8?token=fbd4beb53056a9028863be1274e7d3abbb892aa9-2f28ca3fea3a698224361485940f5371-1771066009-1771062409",
      "stream_path": "edge3/sony-max"
    },
    {
      "channel_number": 106,
      "name": "sony max hd",
      "logo": "http://tvassets.roarzone.info/images/sonymaxhd.png",
      "group": "hindi",
      "url": "https://edge2.roarzone.info:8444/roarzone/edge3/sony-max-hd/index.m3u8?token=c21d5e96788802e8fc13c36374cbc611619fbb76-58f341dd87ff7a1bca93cfd69b313607-1771066009-1771062409",
      "stream_path": "edge3/sony-max-hd"
    },
    {
      "channel_number": 107,
      "name": "sony max 2",
      "logo": "http://tvassets.roarzone.info/images/sonymax2.png",
      "group": "hindi",
      "url": "https://edge2.roarzone.info:8444/roarzone/edge3/sony-max-2/index.m3u8?token=6e4ec3a4e5daa30b12f8b14b9b0e5bb712b246fd-b0eb689b107e8c6a5c18bc309dac9ee3-1771066009-1771062409",
      "stream_path": "edge3/sony-max-2"
    },
    {
      "channel_number": 108,
      "name": "zee tv",
      "logo": "http://tvassets.roarzone.info/images/40.png",
      "group": "hindi",
      "url": "https://edge2.roarzone.info:8444/roarzone/edge3/zee-tv-hd/index.m3u8?token=67778b966c6ecfd3e303c868b6714950c16c5822-7bd9931173bfe113c3ed8236d57e5ff8-1771066009-1771062409",
      "stream_path": "edge3/zee-tv-hd"
    },
    {
      "channel_number": 109,
      "name": "zee cinema",
      "logo": "http://tvassets.roarzone.info/images/76.png",
      "group": "hindi",
      "url": "https://edge2.roarzone.info:8444/roarzone/edge3/zee-cinema-hd/index.m3u8?token=772941e3af810a4be06e4f6b04245c78f37e49ab-ec6d94160931fb8cbadef99bfa00247c-1771066009-1771062409",
      "stream_path": "edge3/zee-cinema-hd"
    },
    {
      "channel_number": 110,
      "name": "zee bollywood",
      "logo": "http://tvassets.roarzone.info/images/94.png",
      "group": "hindi",
      "url": "https://edge2.roarzone.info:8444/roarzone/edge3/zee-bollywood/index.m3u8?token=7cfffdca278e8edca7e9e9fd93d623df63d2cdd1-6c5a4d87ca6e5bbb3b26e1b77443d0c1-1771066009-1771062409",
      "stream_path": "edge3/zee-bollywood"
    },
    {
      "channel_number": 111,
      "name": "zee-anmol",
      "logo": "http://tvassets.roarzone.info/images/zee-anmol.png",
      "group": "hindi",
      "url": "https://edge2.roarzone.info:8444/roarzone/edge3/zee-anmol/index.m3u8?token=fce33b06a47c96dd7f820d8a01566246c323231d-bbf6219fd20e827d056fcad25c404f24-1771066009-1771062409",
      "stream_path": "edge3/zee-anmol"
    },
    {
      "channel_number": 112,
      "name": "hum masala",
      "logo": "http://tvassets.roarzone.info/images/hummasala.png",
      "group": "hindi",
      "url": "https://edge2.roarzone.info:8444/roarzone/edge3/hum-masala/index.m3u8?token=c251c8e50a5ca611bd58861eb59d617d78661fac-a24d8129971dae38ce25c731fec92fbf-1771066009-1771062409",
      "stream_path": "edge3/hum-masala"
    },
    {
      "channel_number": 113,
      "name": "hum sitarey",
      "logo": "http://tvassets.roarzone.info/images/humsitarey.png",
      "group": "hindi",
      "url": "https://edge2.roarzone.info:8444/roarzone/edge3/hum-sitaray/index.m3u8?token=7dacbff602dd8dd3601f078966f458ebabfb7cd6-c91eae1d53ae168393b30ed08ffed4b0-1771066009-1771062409",
      "stream_path": "edge3/hum-sitaray"
    },
    {
      "channel_number": 114,
      "name": "discovery hd",
      "logo": "http://tvassets.roarzone.info/images/43.png",
      "group": "documentary",
      "url": "https://edge2.roarzone.info:8444/roarzone/edge3/discovery-hd/index.m3u8?token=0bf87dacc74b3455a77d0838c0e34c3b74cd0ed8-b9db86be7293ef9622454c07782b42b5-1771066009-1771062409",
      "stream_path": "edge3/discovery-hd"
    },
    {
      "channel_number": 115,
      "name": "discovery science",
      "logo": "http://tvassets.roarzone.info/images/discoveryscience.png",
      "group": "documentary",
      "url": "https://edge2.roarzone.info:8444/roarzone/edge3/discovery-science/index.m3u8?token=3975b86ca3dd3031811e5f6d43997001d963f596-3cfce94f74530b724310eb880be237b1-1771066009-1771062409",
      "stream_path": "edge3/discovery-science"
    },
    {
      "channel_number": 116,
      "name": "discovery turbo",
      "logo": "http://tvassets.roarzone.info/images/discoveryturbo.png",
      "group": "documentary",
      "url": "https://edge2.roarzone.info:8444/roarzone/edge3/discovery-turbo/index.m3u8?token=2a793692835799d3946d9576d2b886034afdd497-025f1f60d3ae38817aa2a2bca133420b-1771066009-1771062409",
      "stream_path": "edge3/discovery-turbo"
    },
    {
      "channel_number": 117,
      "name": "cnn",
      "logo": "http://tvassets.roarzone.info/images/cnn.png",
      "group": "documentary",
      "url": "https://edge2.roarzone.info:8444/roarzone/edge3/cnn/index.m3u8?token=9aef6970c3b528a6ef32b6aea2df818ee35999cc-f3c82b191d6df7fdeeab86095199368e-1771066009-1771062409",
      "stream_path": "edge3/cnn"
    },
    {
      "channel_number": 118,
      "name": "sony bbc earth hd",
      "logo": "http://tvassets.roarzone.info/images/44.png",
      "group": "documentary",
      "url": "https://edge2.roarzone.info:8444/roarzone/edge3/sony-bbc-earth-hd/index.m3u8?token=69d6f4ad3b07f1fce42e26cf9b2444625e095372-34ed0ccc49266a67a13e34c96e97917d-1771066009-1771062409",
      "stream_path": "edge3/sony-bbc-earth-hd"
    },
    {
      "channel_number": 119,
      "name": "animal planet",
      "logo": "http://tvassets.roarzone.info/images/animalplanet.png",
      "group": "documentary",
      "url": "https://edge2.roarzone.info:8444/roarzone/edge3/animal-planet-hd/index.m3u8?token=275089281189cc303133c8957a2c62148d5f94d3-538618f53332af9b5f4e1f6b676a842c-1771066009-1771062409",
      "stream_path": "edge3/animal-planet-hd"
    },
    {
      "channel_number": 120,
      "name": "zee bangla",
      "logo": "http://tvassets.roarzone.info/images/34.png",
      "group": "inbangla",
      "url": "https://edge2.roarzone.info:8444/roarzone/edge3/zee-bangla/index.m3u8?token=fbee90d266047a4888cdead4772bc7bda64b8ccc-e9c057e629341c11c71e6ed337448d22-1771066009-1771062409",
      "stream_path": "edge3/zee-bangla"
    },
    {
      "channel_number": 121,
      "name": "zee bangla cinema",
      "logo": "http://tvassets.roarzone.info/images/29.png",
      "group": "inbangla",
      "url": "https://edge2.roarzone.info:8444/roarzone/edge3/zee-bangla-cinema/index.m3u8?token=b448dfa016fde9538afac65b1f39a71e4cfb558d-a9a25fd621decd5d0a8440877c8a4f7a-1771066009-1771062409",
      "stream_path": "edge3/zee-bangla-cinema"
    },
    {
      "channel_number": 122,
      "name": "sony aath",
      "logo": "http://tvassets.roarzone.info/images/33.png",
      "group": "inbangla",
      "url": "https://edge2.roarzone.info:8444/roarzone/edge3/sony-aath/index.m3u8?token=b85266d8584b2ee92b859713e6e943370dda93c2-66e6675a527ba634dfff196efebe0144-1771066009-1771062409",
      "stream_path": "edge3/sony-aath"
    },
    {
      "channel_number": 123,
      "name": "cartoon network hd",
      "logo": "http://tvassets.roarzone.info/images/cartoon-network-hd.webp",
      "group": "kids",
      "url": "https://edge2.roarzone.info:8444/roarzone/edge3/cartoon-network-hd/index.m3u8?token=81919fe230d1730111bddb7c6f4c3a76a3aa5a71-b2f0da6aa2d47d2303203f4193291d05-1771066009-1771062409",
      "stream_path": "edge3/cartoon-network-hd"
    },
    {
      "channel_number": 124,
      "name": "discovery kids",
      "logo": "http://tvassets.roarzone.info/images/discoverykids.png",
      "group": "kids",
      "url": "https://edge2.roarzone.info:8444/roarzone/edge3/discovery-kids/index.m3u8?token=0ff4c0db313cb43897037f7982f449914e77bd2d-0a78a3449fca05541036ee176ca83790-1771066009-1771062409",
      "stream_path": "edge3/discovery-kids"
    },
    {
      "channel_number": 125,
      "name": "sony yay",
      "logo": "http://tvassets.roarzone.info/images/sonyyay.png",
      "group": "kids",
      "url": "https://edge2.roarzone.info:8444/roarzone/edge3/sony-yay/index.m3u8?token=8823abb549af62240f8251d15df1834245f1bcda-7cd27bfdc44e81a60d9d491e3ee96e43-1771066009-1771062409",
      "stream_path": "edge3/sony-yay"
    },
    {
      "channel_number": 126,
      "name": "tlc hd",
      "logo": "http://tvassets.roarzone.info/images/tlc-hd.webp",
      "group": "english",
      "url": "https://edge2.roarzone.info:8444/roarzone/edge3/tlc-hd/index.m3u8?token=23fabe97f1efbe7c76fa052187dcab19dbc4381c-3649c10fdb127e1cbbb450ba10376e90-1771066009-1771062409",
      "stream_path": "edge3/tlc-hd"
    },
    {
      "channel_number": 127,
      "name": "b4u music",
      "logo": "http://tvassets.roarzone.info/images/b4umusic.png",
      "group": "music",
      "url": "https://edge2.roarzone.info:8444/roarzone/edge3/b4u-music/index.m3u8?token=94e2b981fdca422a5ce63b6e54f40928cb12a053-7ccb367f3a1cb1eca3e464b8852d0f99-1771066009-1771062409",
      "stream_path": "edge3/b4u-music"
    },
    {
      "channel_number": 128,
      "name": "jamuna tv",
      "logo": "http://tvassets.roarzone.info/images/13.png",
      "group": "bangla",
      "url": "https://edge2.roarzone.info:8444/roarzone/edge3/jamuna-tv/index.m3u8?token=f773e04a8e6a355c97e17c88b7e2b16dcbd7025a-b092b4e03389162195f0be989242275c-1771066009-1771062409",
      "stream_path": "edge3/jamuna-tv"
    },
    {
      "channel_number": 129,
      "name": "channel s",
      "logo": "http://tvassets.roarzone.info/images/channel-s.png",
      "group": "bangla",
      "url": "https://edge2.roarzone.info:8444/roarzone/edge3/channel-s/index.m3u8?token=d1a294fc681547bb7e894f7ba133934f7b95306f-b9527638a7a422a9a9aef00b58c054cd-1771066009-1771062409",
      "stream_path": "edge3/channel-s"
    },
    {
      "channel_number": 130,
      "name": "global tv",
      "logo": "http://tvassets.roarzone.info/images/global-tv.png",
      "group": "bangla",
      "url": "https://edge2.roarzone.info:8444/roarzone/edge3/global-tv/index.m3u8?token=7c7d3b9d1179bc5be511688b35563619fb6e4742-2a57a1f8e9753785d10aa00f9fc64e93-1771066009-1771062409",
      "stream_path": "edge3/global-tv"
    },
    {
      "channel_number": 131,
      "name": "ananda tv",
      "logo": "http://tvassets.roarzone.info/images/16.png",
      "group": "bangla",
      "url": "https://edge2.roarzone.info:8444/roarzone/edge3/ananda-tv/index.m3u8?token=31ea62daaa1499c1fb71d3dd227fed72d03847f0-e86358051cbe65095ac3ff8024c7d641-1771066009-1771062409",
      "stream_path": "edge3/ananda-tv"
    },
    {
      "channel_number": 132,
      "name": "bangla tv",
      "logo": "http://tvassets.roarzone.info/images/19.png",
      "group": "bangla",
      "url": "https://edge2.roarzone.info:8444/roarzone/edge3/bangla-tv/index.m3u8?token=ba3e02dec2d853ac33c98f27bb58a4266e76f36a-b449ebe9492ceab7f2634f87fbdd89fa-1771066009-1771062409",
      "stream_path": "edge3/bangla-tv"
    },
    {
      "channel_number": 133,
      "name": "channel i",
      "logo": "http://tvassets.roarzone.info/images/6.png",
      "group": "bangla",
      "url": "https://edge2.roarzone.info:8444/roarzone/edge3/channel-i/index.m3u8?token=216aafd43c4254e07f1b3cfc9d2a543bbe8c0154-88c2659eeece328af48bcb294df142b9-1771066009-1771062409",
      "stream_path": "edge3/channel-i"
    },
    {
      "channel_number": 134,
      "name": "independent tv",
      "logo": "http://tvassets.roarzone.info/images/12.png",
      "group": "bangla",
      "url": "https://edge2.roarzone.info:8444/roarzone/edge3/independent-tv/index.m3u8?token=025b4c22b23675e8e5c3ab3930ca7e3044c9575a-e3c89e00af1d63160fc8b8dad88c894e-1771066009-1771062409",
      "stream_path": "edge3/independent-tv"
    },
    {
      "channel_number": 135,
      "name": "movie bangla tv",
      "logo": "http://tvassets.roarzone.info/images/86.png",
      "group": "bangla",
      "url": "https://edge2.roarzone.info:8444/roarzone/edge3/movie-bangla/index.m3u8?token=3a7cab8567246ae4abb239561ffd0f9a47bea98a-6eda02644edd7b985bea7f3cebe93d6f-1771066009-1771062409",
      "stream_path": "edge3/movie-bangla"
    },
    {
      "channel_number": 136,
      "name": "bijoy-tv",
      "logo": "http://tvassets.roarzone.info/images/bijoy-tv.jpg",
      "group": "bangla",
      "url": "https://edge2.roarzone.info:8444/roarzone/edge3/bijoy-tv/index.m3u8?token=3db07ec2c545c73857e4b0e2d10d07eb809900e1-b5e0e418222e276438c1814e4efafcfa-1771066009-1771062409",
      "stream_path": "edge3/bijoy-tv"
    },
    {
      "channel_number": 137,
      "name": "sony tv",
      "logo": "http://tvassets.roarzone.info/images/38.png",
      "group": "hindi",
      "url": "https://edge2.roarzone.info:8444/roarzone/edge3/sony-entertainment-television-hd/index.m3u8?token=5e3026f82b0f76372167e573d787025d12e5e4b1-dbd3d7dd2d83746cecb5c4c8d4c72c17-1771066009-1771062409",
      "stream_path": "edge3/sony-entertainment-television-hd"
    },
    {
      "channel_number": 138,
      "name": "and pictures",
      "logo": "http://tvassets.roarzone.info/images/100.png",
      "group": "hindi",
      "url": "https://edge2.roarzone.info:8444/roarzone/edge3/pictures-hd/index.m3u8?token=e5fbec13cf5ccb2493298a65959cc0425627ebec-c195711c0a72222e53f590315e762727-1771066009-1771062409",
      "stream_path": "edge3/pictures-hd"
    },
    {
      "channel_number": 139,
      "name": "hum tv",
      "logo": "http://tvassets.roarzone.info/images/humtv.png",
      "group": "hindi",
      "url": "https://edge2.roarzone.info:8444/roarzone/edge3/hum/index.m3u8?token=0acd6a56834be2992aba8bd7b0958d8a1b9d4fa9-89e0c639f93c6bfe3131e2c1e932cabb-1771066009-1771062409",
      "stream_path": "edge3/hum"
    },
    {
      "channel_number": 140,
      "name": "b4u movies",
      "logo": "http://tvassets.roarzone.info/images/b4umovies.png",
      "group": "hindi",
      "url": "https://edge2.roarzone.info:8444/roarzone/edge3/b4u-movies-apac/index.m3u8?token=f287a0b54ea4cba4099167e0148ac6d96800502d-4fb1140062c374d1d0a1ed14a19b8a66-1771066009-1771062409",
      "stream_path": "edge3/b4u-movies-apac"
    },
    {
      "channel_number": 141,
      "name": "sony sab",
      "logo": "http://tvassets.roarzone.info/images/36.png",
      "group": "hindi",
      "url": "https://edge2.roarzone.info:8444/roarzone/edge3/sony-sab-hd/index.m3u8?token=9f827ef65bce046ca39c2ced924a5344c6a9d802-e2d4245d8bf85b07e65436c2b25609c0-1771066009-1771062409",
      "stream_path": "edge3/sony-sab-hd"
    },
    {
      "channel_number": 142,
      "name": "discovery hd investigation",
      "logo": "http://tvassets.roarzone.info/images/discoveryhdInvestigation.png",
      "group": "documentary",
      "url": "https://edge2.roarzone.info:8444/roarzone/edge3/investigation-discovery-hd/index.m3u8?token=00d9a19a3dfef89227af3b98c156afd39fcf34b3-7e75dc68cf5f9b188b3c8fa21d43ddae-1771066009-1771062409",
      "stream_path": "edge3/investigation-discovery-hd"
    },
    {
      "channel_number": 143,
      "name": "cartoon network",
      "logo": "http://tvassets.roarzone.info/images/cartoon-network.webp",
      "group": "kids",
      "url": "https://edge2.roarzone.info:8444/roarzone/edge3/cartoon-network/index.m3u8?token=805f301542fb370473d1ff8140823144e4e1671f-88ea79a27bb7638cadd4afbe89e0cee7-1771066009-1771062409",
      "stream_path": "edge3/cartoon-network"
    },
    {
      "channel_number": 144,
      "name": "pogo",
      "logo": "http://tvassets.roarzone.info/images/pogo.png",
      "group": "kids",
      "url": "https://edge2.roarzone.info:8444/roarzone/edge3/pogo/index.m3u8?token=946f77f3b28596c456a2b9a87876959f7c5da9c4-38864a457eaac08366d35def2a5eee1a-1771066009-1771062409",
      "stream_path": "edge3/pogo"
    },
    {
      "channel_number": 145,
      "name": "zee cafe hd",
      "logo": "http://tvassets.roarzone.info/images/69.png",
      "group": "english",
      "url": "https://edge2.roarzone.info:8444/roarzone/edge3/zee-cafe/index.m3u8?token=3b0a6b0b7b8ff54249158188d1d13467b31d7800-d7af0d11a6aac9e80059791361fcd408-1771066009-1771062409",
      "stream_path": "edge3/zee-cafe"
    },
    {
      "channel_number": 146,
      "name": "sony pix",
      "logo": "http://tvassets.roarzone.info/images/41.png",
      "group": "english",
      "url": "https://edge2.roarzone.info:8444/roarzone/edge3/sony-pix-hd/index.m3u8?token=0eccd68e31556ae10ac3f82a5c1dedd4a63bd843-ad5516223efdf9436dbb9885e982c0e1-1771066009-1771062409",
      "stream_path": "edge3/sony-pix-hd"
    },
    {
      "channel_number": 147,
      "name": "zing",
      "logo": "http://tvassets.roarzone.info/images/93.png",
      "group": "music",
      "url": "https://edge2.roarzone.info:8444/roarzone/edge3/zing/index.m3u8?token=d5ffa22b4289b5dcdbebd15e884bc0edff3b8c12-2dbf17ccacdbe85bfc6acde77a141e13-1771066009-1771062409",
      "stream_path": "edge3/zing"
    },
    {
      "channel_number": 148,
      "name": "asian tv",
      "logo": "http://tvassets.roarzone.info/images/62.png",
      "group": "bangla",
      "url": "https://edge2.roarzone.info:8444/roarzone/edge3/asian-tv/index.m3u8?token=8c43508e75d0ce3890debae6cb6e478ab7cb9198-7f3346580bd1427c7a8098ccd5d5a275-1771066009-1771062409",
      "stream_path": "edge3/asian-tv"
    },
    {
      "channel_number": 149,
      "name": "euro sports",
      "logo": "http://tvassets.roarzone.info/images/euro_sports_hd.png",
      "group": "sports",
      "url": "https://edge2.roarzone.info:8444/roarzone/edge3/euro-sport-hd/index.m3u8?token=5e2fb31043bbaafa46bf6527370b3b50b26836ca-8aec14bbb1ee7182689de6ff97310fb6-1771066009-1771062409",
      "stream_path": "edge3/euro-sport-hd"
    },
    {
      "channel_number": 150,
      "name": "ten cricket",
      "logo": "http://tvassets.roarzone.info/images/ten_cricket.png",
      "group": "sports",
      "url": "https://edge2.roarzone.info:8444/roarzone/edge3/sony-ten-cricket/index.m3u8?token=be763adbe4b49a0ee71ef2f2b15b816bb8c0ae25-b1c0c2940167918e0bc28960b33adb09-1771066009-1771062409",
      "stream_path": "edge3/sony-ten-cricket"
    },
    {
      "channel_number": 151,
      "name": "zee action",
      "logo": "http://tvassets.roarzone.info/images/90.png",
      "group": "hindi",
      "url": "https://edge2.roarzone.info:8444/roarzone/edge3/zee-action/index.m3u8?token=b45c3c266972c65f5365e701f23611e7a94113ff-7aa31be091018e9af6df93753dd37afc-1771066009-1771062409",
      "stream_path": "edge3/zee-action"
    },
    {
      "channel_number": 152,
      "name": "and tv hd",
      "logo": "http://tvassets.roarzone.info/images/74.png",
      "group": "hindi",
      "url": "https://edge2.roarzone.info:8444/roarzone/edge3/tv-hd/index.m3u8?token=ae00165c383fbcce542b178026c29ef6e494053d-522e5c13d7c107340047924534063560-1771066009-1771062409",
      "stream_path": "edge3/tv-hd"
    },
    {
      "channel_number": 153,
      "name": "banglavision tv",
      "logo": "http://tvassets.roarzone.info/images/3.png",
      "group": "bangla",
      "url": "https://edge2.roarzone.info:8444/roarzone/edge2/banglavision/index.m3u8?token=658f44971c973d93b998de008a24dfbd6decb8b5-08a1cfdb544e29c80bce75e1555cf6b5-1771066009-1771062409",
      "stream_path": "edge2/banglavision"
    },
    {
      "channel_number": 154,
      "name": "star gold",
      "logo": "http://tvassets.roarzone.info/images/75.png",
      "group": "hindi",
      "url": "https://edge2.roarzone.info:8444/roarzone/edge2/star-gold/index.m3u8?token=26180fa4f3bb2ecff80361e9d03c8ce8109f8b91-cc6743ac966f67eccb6d586f1754789e-1771066009-1771062409",
      "stream_path": "edge2/star-gold"
    }
  ]
}